cuba_weather_municipality/__init__.py
cuba_weather_municipality/data_providers/__init__.py
cuba_weather_municipality/data_providers/municipalities.py
cuba_weather_municipality/models/__init__.py
cuba_weather_municipality/models/municipality_model.py
cuba_weather_municipality/repositories/__init__.py
cuba_weather_municipality/repositories/municipality_repository.py
cuba_weather_municipality/utils/__init__.py
cuba_weather_municipality/utils/damerau_levenshtein.py
cuba_weather_municipality/utils/municipality_curator.py
cuba_weather_municipality-0.1.4.dist-info/LICENSE
cuba_weather_municipality-0.1.4.dist-info/METADATA
cuba_weather_municipality-0.1.4.dist-info/WHEEL
cuba_weather_municipality-0.1.4.dist-info/top_level.txt
cuba_weather_municipality-0.1.4.dist-info/RECORD
