Metadata-Version: 2.1
Name: cuba-weather-municipality
Version: 0.1.4
Summary: A tool implemented in Python for the Cuba Weather project to work with the municipalities of Cuba.
Home-page: https://github.com/cuba-weather/cuba-weather-municipality-python
Author: Cuban Open Source Community
License: MIT
Platform: UNKNOWN
Classifier: Programming Language :: Python :: 3
Classifier: License :: OSI Approved :: MIT License
Classifier: Operating System :: OS Independent
Requires-Python: >=3.6
